cbz_generator/__init__.py
cbz_generator/create_cbz_archive.py
cbz_generator-1.0.0.dist-info/LICENSE
cbz_generator-1.0.0.dist-info/METADATA
cbz_generator-1.0.0.dist-info/WHEEL
cbz_generator-1.0.0.dist-info/top_level.txt
cbz_generator-1.0.0.dist-info/RECORD
