Metadata-Version: 2.1
Name: cbz_generator
Version: 1.0.0
Summary: Utility for converting images into a CBZ archive individually or in bulk.
Author: Tyler C
Author-email: Tyler C <contact@tycro.io>
Project-URL: Homepage, https://github.com/croozelberryTea/cbz-generator
Project-URL: Issues, https://github.com/croozelberryTea/cbz-generator/issues
Classifier: Programming Language :: Python :: 3
Classifier: License :: OSI Approved :: MIT License
Classifier: Operating System :: OS Independent
Requires-Python: >=3.8
License-File: LICENSE
